washingmachine.v
module washingmachine(
    input clk,reset,start,pause,door_open,power_cut,
    output reg[2:0] state,
    output reg motor,valve,drain_pump,spin_motor
);

parameter IDLE = 3'b000;
parameter FILL_WATER = 3'b001;
parameter WASH = 3'b010;
parameter DRAIN = 3'b011;
parameter RINSE = 3'b100;
parameter SPIN = 3'b101;
parameter DONE = 3'b110;

reg[2:0] next_state;
reg[31:0] timer;

always @(posedge clk or posedge reset) begin
  if(reset) begin
    state <= IDLE;
    timer <= 0;
  end
  else if(power_cut) begin
    state <= state;
  end 
  else if(door_open) begin
    state <= IDLE;
  end
  else if(pause) begin
    state <= state;
  end
  else begin
    state <= next_state;
  end
end

always @(*) begin
    case(state)
        IDLE: next_state = (start)?FILL_WATER:IDLE;
        FILL_WATER : next_state =(timer >= 5)?WASH:FILL_WATER;
        WASH : next_state=(timer >= 10)? DRAIN:WASH;
        DRAIN:      next_state = (timer >= 5) ? RINSE : DRAIN;
        RINSE:      next_state = (timer >= 7) ? SPIN : RINSE;
        SPIN:       next_state = (timer >= 8) ? DONE : SPIN;
        DONE:       next_state = IDLE;
        default:    next_state = IDLE; 
    endcase    
end

always @(posedge clk) begin
    if (state != next_state) 
        timer <= 0;
    else
        timer <= timer + 1;
end

always @(state) begin
    // Default off
    motor = 0;
    valve = 0;
    drain_pump = 0;
    spin_motor = 0;
    
    case (state)
        FILL_WATER: valve = 1;
        WASH: motor = 1;
        DRAIN: drain_pump = 1;
        RINSE:begin motor=1; valve = 1;
        end
        SPIN: spin_motor = 1;
        DONE: ; // No action needed
    endcase
end
endmodule

washingmachine_tb.v
`timescale 1ns/1ps
`include "washingmachine.v"

module washingmachine_tb;
    reg clk, reset, start, pause, door_open, power_cut;
    wire motor, valve, drain_pump, spin_motor;
    wire [2:0] state;

    washingmachine uut (
        .clk(clk),
        .reset(reset),
        .start(start),
        .pause(pause),
        .door_open(door_open),
        .power_cut(power_cut),
        .state(state),
        .motor(motor),
        .valve(valve),
        .drain_pump(drain_pump),
        .spin_motor(spin_motor)
    );

    always #5 clk = ~clk;  // 10ns period (100MHz clock)

    initial begin
        $dumpfile("washingmachine_tb.vcd");
        $dumpvars(0, washingmachine_tb);

        clk = 0;
        reset = 1; #10;  // Reset system
        reset=0;
        // Start washing machine
        start = 1;

        // Wait for FILL_WATER (5 cycles)
        #50;
        if (state != uut.FILL_WATER) $display("ERROR: Expected FILL_WATER but got %b", state);

        // Wait for WASH (10 cycles)
        #100;
        if (state != uut.WASH) $display("ERROR: Expected WASH but got %b", state);

        // Wait for DRAIN (5 cycles)
        #50;
        if (state != uut.DRAIN) $display("ERROR: Expected DRAIN but got %b", state);

        // Wait for RINSE (7 cycles)
        #70;
        if (state != uut.RINSE) $display("ERROR: Expected RINSE but got %b", state);

        // Wait for SPIN (8 cycles)
        #80;
        if (state != uut.SPIN) $display("ERROR: Expected SPIN but got %b", state);

        // Wait for DONE
        #10;
        if (state != uut.DONE) $display("ERROR: Expected DONE but got %b", state);
        
        // End test
        $display("✅ Test completed successfully!");
        $finish;
    end

    initial begin
        $monitor("Time=%0t | State=%b | Motor=%b | Valve=%b | Drain=%b | Spin=%b",
                 $time, state, motor, valve, drain_pump, spin_motor);
    end

endmodule

washingmachine_tb.vcd
$date
	Wed Mar 12 11:40:15 2025
$end
$version
	Icarus Verilog
$end
$timescale
	1ps
$end
$scope module washingmachine_tb $end
$var wire 1 ! drain_pump $end
$var wire 1 " motor $end
$var wire 1 # spin_motor $end
$var wire 3 $ state [2:0] $end
$var wire 1 % valve $end
$var reg 1 & clk $end
$var reg 1 ' door_open $end
$var reg 1 ( pause $end
$var reg 1 ) power_cut $end
$var reg 1 * reset $end
$var reg 1 + start $end
$scope module uut $end
$var wire 1 , clk $end
$var wire 1 - door_open $end
$var wire 1 . pause $end
$var wire 1 / power_cut $end
$var wire 1 0 reset $end
$var wire 1 1 start $end
$var reg 1 2 drain_pump $end
$var reg 1 3 motor $end
$var reg 3 4 next_state [2:0] $end
$var reg 1 5 spin_motor $end
$var reg 3 6 state [2:0] $end
$var reg 32 7 timer [31:0] $end
$var reg 1 8 valve $end
$upscope $end
$upscope $end
$enddefinitions $end
#0
$dumpvars
08
b0 7
b0 6
05
b0x 4
03
02
x1
10
x/
x.
x-
0,
x+
1*
x)
x(
x'
0&
0%
b0 $
0#
0"
0!
$end
#5000
b1 7
1&
1,
#10000
b1 4
0&
0,
1+
11
0*
00
#15000
18
1%
b0 7
b1 6
b1 $
1&
1,
#20000
0&
0,
#25000
b1 7
1&
1,
#30000
0&
0,
#35000
b10 7
1&
1,
#40000
0&
0,
#45000
b11 7
1&
1,
#50000
0&
0,
#55000
b100 7
1&
1,
#60000
0&
0,
#65000
b10 4
b101 7
1&
1,
#70000
0&
0,
#75000
13
1"
08
0%
b0 7
b10 6
b10 $
1&
1,
#80000
0&
0,
#85000
b1 7
1&
1,
#90000
0&
0,
#95000
b10 7
1&
1,
#100000
0&
0,
#105000
b11 7
1&
1,
#110000
0&
0,
#115000
b100 7
1&
1,
#120000
0&
0,
#125000
b101 7
1&
1,
#130000
0&
0,
#135000
b110 7
1&
1,
#140000
0&
0,
#145000
b111 7
1&
1,
#150000
0&
0,
#155000
b1000 7
1&
1,
#160000
0&
0,
#165000
b1001 7
1&
1,
#170000
0&
0,
#175000
b11 4
b1010 7
1&
1,
#180000
0&
0,
#185000
12
1!
03
0"
b0 7
b11 6
b11 $
1&
1,
#190000
0&
0,
#195000
b1 7
1&
1,
#200000
0&
0,
#205000
b10 7
1&
1,
#210000
0&
0,
#215000
b11 7
1&
1,
#220000
0&
0,
#225000
b100 7
1&
1,
#230000
0&
0,
#235000
b100 4
b101 7
1&
1,
#240000
0&
0,
#245000
18
1%
13
1"
02
0!
b0 7
b100 6
b100 $
1&
1,
#250000
0&
0,
#255000
b1 7
1&
1,
#260000
0&
0,
#265000
b10 7
1&
1,
#270000
0&
0,
#275000
b11 7
1&
1,
#280000
0&
0,
#285000
b100 7
1&
1,
#290000
0&
0,
#295000
b101 7
1&
1,
#300000
0&
0,
#305000
b110 7
1&
1,
#310000
0&
0,
#315000
b101 4
b111 7
1&
1,
#320000
0&
0,
#325000
15
1#
08
0%
03
0"
b0 7
b101 6
b101 $
1&
1,
#330000
0&
0,
#335000
b1 7
1&
1,
#340000
0&
0,
#345000
b10 7
1&
1,
#350000
0&
0,
#355000
b11 7
1&
1,
#360000
0&
0,
#365000
b100 7
1&
1,
